exalt/__init__.py
exalt-0.1.2.dist-info/LICENSE
exalt-0.1.2.dist-info/WHEEL
exalt-0.1.2.dist-info/METADATA
exalt-0.1.2.dist-info/RECORD
